Metadata-Version: 2.1
Name: thiticanfunctions
Version: 0.1.0
Summary: ฟังก์ชันของ Can Thitipong
Home-page: 
Author: Can Thitipong
Author-email: th.yingyong@gmail.com
License: MIT
Keywords: thitican
Classifier: Development Status :: 5 - Production/Stable
Classifier: Intended Audience :: Education
Classifier: Operating System :: Microsoft :: Windows :: Windows 11
Classifier: License :: OSI Approved :: MIT License
Classifier: Programming Language :: Python :: 3
License-File: LICENCE.txt
